cdbw/__init__.py
cdbw/cdbw.py
cdbw-0.2.dist-info/LICENSE
cdbw-0.2.dist-info/METADATA
cdbw-0.2.dist-info/WHEEL
cdbw-0.2.dist-info/top_level.txt
cdbw-0.2.dist-info/RECORD
