Metadata-Version: 2.1
Name: cdbw
Version: 0.2
Summary: Compute the CDbw validity index
Home-page: https://github.com/alashkov83/CDbw
Author: Sergey Rubinsky, Alexander Lashkov, Polina Eistrikh-Heller
Author-email: alashkov83@gmail.com
Maintainer: Alexander Lashkov
License: MIT License
Keywords: clustering,cluster analysis,cluster validation
Platform: any
Classifier: Development Status :: 4 - Beta
Classifier: Intended Audience :: Science/Research
Classifier: Intended Audience :: Developers
Classifier: License :: OSI Approved
Classifier: Programming Language :: Python
Classifier: Topic :: Software Development
Classifier: Topic :: Scientific/Engineering
Classifier: Operating System :: Microsoft :: Windows
Classifier: Operating System :: POSIX
Classifier: Operating System :: Unix
Classifier: Operating System :: MacOS
Classifier: Programming Language :: Python :: 2.7
Classifier: Programming Language :: Python :: 3.4
Requires-Python: >=2.7
Requires-Dist: scipy
Requires-Dist: numpy (>=1.14.2)
